Loading3D.py
SMLLOADING3D-0.4.dist-info/LICENCE.txt
SMLLOADING3D-0.4.dist-info/METADATA
SMLLOADING3D-0.4.dist-info/WHEEL
SMLLOADING3D-0.4.dist-info/top_level.txt
SMLLOADING3D-0.4.dist-info/RECORD
