Metadata-Version: 2.1
Name: SMLLOADING3D
Version: 0.4
Summary: loading 3D
Home-page: UNKNOWN
Author: Mr. Hanh
License: LICENSE.txt
Platform: UNKNOWN
Classifier: Programming Language :: Python :: 3.8
Classifier: License :: OSI Approved :: MIT License
Requires-Dist: numba
